optibioseq/__init__.py
optibioseq/__main__.py
optibioseq/abc.py
optibioseq/bce.py
optibioseq/bepi.py
optibioseq/iedb1.py
optibioseq/iedb2.py
optibioseq-0.2.1.dist-info/METADATA
optibioseq-0.2.1.dist-info/WHEEL
optibioseq-0.2.1.dist-info/RECORD
