Metadata-Version: 2.4
Name: optibioseq
Version: 0.2.1
Summary: 
Author: Ivan Corona Guerrero
Author-email: icg.microbiologia@gmail.com
Requires-Python: >=3.12,<4.0
Classifier: Programming Language :: Python :: 3
Classifier: Programming Language :: Python :: 3.12
Classifier: Programming Language :: Python :: 3.13
Classifier: Programming Language :: Python :: 3.14
Requires-Dist: bs4 (>=0.0.1,<0.0.2)
Requires-Dist: numpy (>=1.22.2,<2.0.0)
Requires-Dist: openpyxl (>=3.0.9,<4.0.0)
Requires-Dist: pandas (>=1.4.0,<2.0.0)
